odoo/addons/stock_dynamic_routing_delivery_procurement_group_carrier/README.rst
odoo/addons/stock_dynamic_routing_delivery_procurement_group_carrier/__init__.py
odoo/addons/stock_dynamic_routing_delivery_procurement_group_carrier/__manifest__.py
odoo/addons/stock_dynamic_routing_delivery_procurement_group_carrier/i18n/it.po
odoo/addons/stock_dynamic_routing_delivery_procurement_group_carrier/i18n/stock_dynamic_routing_delivery_procurement_group_carrier.pot
odoo/addons/stock_dynamic_routing_delivery_procurement_group_carrier/models/__init__.py
odoo/addons/stock_dynamic_routing_delivery_procurement_group_carrier/models/stock_move.py
odoo/addons/stock_dynamic_routing_delivery_procurement_group_carrier/readme/CONTRIBUTORS.md
odoo/addons/stock_dynamic_routing_delivery_procurement_group_carrier/readme/DESCRIPTION.md
odoo/addons/stock_dynamic_routing_delivery_procurement_group_carrier/static/description/icon.png
odoo/addons/stock_dynamic_routing_delivery_procurement_group_carrier/static/description/index.html
odoo/addons/stock_dynamic_routing_delivery_procurement_group_carrier/tests/__init__.py
odoo/addons/stock_dynamic_routing_delivery_procurement_group_carrier/tests/test_carrier_propagation.py
odoo_addon_stock_dynamic_routing_delivery_procurement_group_carrier-18.0.1.1.0.2.dist-info/METADATA
odoo_addon_stock_dynamic_routing_delivery_procurement_group_carrier-18.0.1.1.0.2.dist-info/WHEEL
odoo_addon_stock_dynamic_routing_delivery_procurement_group_carrier-18.0.1.1.0.2.dist-info/top_level.txt
odoo_addon_stock_dynamic_routing_delivery_procurement_group_carrier-18.0.1.1.0.2.dist-info/RECORD
