Metadata-Version: 2.1
Name: odoo-addon-stock_dynamic_routing_delivery_procurement_group_carrier
Version: 18.0.1.1.0.2
Requires-Python: >=3.10
Requires-Dist: odoo-addon-delivery_procurement_group_carrier==18.0.*
Requires-Dist: odoo-addon-stock_dynamic_routing_delivery==18.0.*
Requires-Dist: odoo==18.0.*
Summary: Use the carrier set on the procurement group for propagation
Home-page: https://github.com/OCA/stock-logistics-workflow
License: AGPL-3
Author: Camptocamp, BCIM, Odoo Community Association (OCA)
Author-email: support@odoo-community.org
Classifier: Programming Language :: Python
Classifier: Framework :: Odoo
Classifier: Framework :: Odoo :: 18.0
Classifier: License :: OSI Approved :: GNU Affero General Public License v3
